IQA_pytorch/CW_SSIM.py
IQA_pytorch/DISTS.py
IQA_pytorch/FSIM.py
IQA_pytorch/GMSD.py
IQA_pytorch/LPIPSvgg.py
IQA_pytorch/MAD.py
IQA_pytorch/MS_SSIM.py
IQA_pytorch/NLPD.py
IQA_pytorch/SSIM.py
IQA_pytorch/SteerPyrComplex.py
IQA_pytorch/SteerPyrSpace.py
IQA_pytorch/SteerPyrUtils.py
IQA_pytorch/VIF.py
IQA_pytorch/VIFs.py
IQA_pytorch/VSI.py
IQA_pytorch/__init__.py
IQA_pytorch/utils.py
IQA_pytorch/weights/DISTS.pt
IQA_pytorch/weights/LPIPSvgg.pt
IQA_pytorch-0.1.data/data/DISTS.pt
IQA_pytorch-0.1.data/data/LPIPSvgg.pt
IQA_pytorch-0.1.dist-info/LICENSE
IQA_pytorch-0.1.dist-info/METADATA
IQA_pytorch-0.1.dist-info/WHEEL
IQA_pytorch-0.1.dist-info/top_level.txt
IQA_pytorch-0.1.dist-info/RECORD
