Metadata-Version: 2.1
Name: IQA-pytorch
Version: 0.1
Summary: IQA models in PyTorch
Home-page: https://github.com/dingkeyan93/IQA-pytorch
Author: Keyan Ding
Author-email: dingkeyan93@outlook.com
License: MIT
Keywords: pytorch,similarity,IQA,metric,image-quality
Platform: python
Requires-Dist: torch (>=1.0)
